Metadata-Version: 2.1
Name: TEST_upload_to_test_functionality
Version: 0.0.1
Summary: just a test
Author: Adéla Dolníček
License: GNU PL
